macrometa_source_postgres/__init__.py
macrometa_source_postgres/connection.py
macrometa_source_postgres/helper.py
macrometa_source_postgres/sync_strategies/__init__.py
macrometa_source_postgres/sync_strategies/common.py
macrometa_source_postgres/sync_strategies/full_table.py
macrometa_source_postgres/sync_strategies/log_based.py
macrometa_source_postgres/sync_strategies/sample_data.py
macrometa_source_postgres-1.0.0.dist-info/entry_points.txt
macrometa_source_postgres-1.0.0.dist-info/LICENSE
macrometa_source_postgres-1.0.0.dist-info/WHEEL
macrometa_source_postgres-1.0.0.dist-info/METADATA
macrometa_source_postgres-1.0.0.dist-info/RECORD
